UdemyCalculator/__init__.py
UdemyCalculator/calculator.py
tests/__init__.py
tests/test_calculator.py
UdemyCalculator_aag-1.0.0.dist-info/LICENCE
UdemyCalculator_aag-1.0.0.dist-info/METADATA
UdemyCalculator_aag-1.0.0.dist-info/WHEEL
UdemyCalculator_aag-1.0.0.dist-info/top_level.txt
UdemyCalculator_aag-1.0.0.dist-info/RECORD
