Metadata-Version: 2.1
Name: UdemyCalculator-aag
Version: 1.0.0
Summary: This is my udemy calculator package
Home-page: 
Author: Alessandro Guarita
Requires-Python: >=3.6
License-File: LICENCE
